{
  "presentationTable" : {
    "name" : "Delivery",
    "presentationColumns" : [ {
      "name" : "Delivery Id",
      "sourceLogicalColumn" : "logicalColumn:SSYS.Dim - Delivery.Delivery Id",
      "localization" : {
        "localizationKey" : "Delivery Id",
        "nameVariable" : "VALUEOF(NQ_SESSION.CN_SSYS_-_Sales_Orders_Delivery_Delivery_Id)",
        "descriptionVariable" : "VALUEOF(NQ_SESSION.CD_SSYS_-_Sales_Orders_Delivery_Delivery_Id)"
      }
    }, {
      "name" : "Delivery Name",
      "sourceLogicalColumn" : "logicalColumn:SSYS.Dim - Delivery.Delivery Name",
      "localization" : {
        "localizationKey" : "Delivery Name",
        "nameVariable" : "VALUEOF(NQ_SESSION.CN_SSYS_-_Sales_Orders_Delivery_Delivery_Name)",
        "descriptionVariable" : "VALUEOF(NQ_SESSION.CD_SSYS_-_Sales_Orders_Delivery_Delivery_Name)"
      }
    }, {
      "name" : "Accepted Date",
      "sourceLogicalColumn" : "logicalColumn:SSYS.Dim - Delivery.Accepted Date",
      "localization" : {
        "localizationKey" : "Accepted Date",
        "nameVariable" : "VALUEOF(NQ_SESSION.CN_SSYS_-_Sales_Orders_Delivery_Accepted_Date)",
        "descriptionVariable" : "VALUEOF(NQ_SESSION.CD_SSYS_-_Sales_Orders_Delivery_Accepted_Date)"
      }
    }, {
      "name" : "Confirmation Date",
      "description" : "Confirm Date",
      "sourceLogicalColumn" : "logicalColumn:SSYS.Dim - Delivery.Confirmation Date",
      "localization" : {
        "localizationKey" : "Confirmation Date",
        "nameVariable" : "VALUEOF(NQ_SESSION.CN_SSYS_-_Sales_Orders_Delivery_Confirmation_Date)",
        "descriptionVariable" : "VALUEOF(NQ_SESSION.CD_SSYS_-_Sales_Orders_Delivery_Confirmation_Date)"
      }
    }, {
      "name" : "Delivered Date",
      "sourceLogicalColumn" : "logicalColumn:SSYS.Dim - Delivery.Delivered Date",
      "localization" : {
        "localizationKey" : "Delivered Date",
        "nameVariable" : "VALUEOF(NQ_SESSION.CN_SSYS_-_Sales_Orders_Delivery_Delivered_Date)",
        "descriptionVariable" : "VALUEOF(NQ_SESSION.CD_SSYS_-_Sales_Orders_Delivery_Delivered_Date)"
      }
    }, {
      "name" : "Delivery Creation Date",
      "sourceLogicalColumn" : "logicalColumn:SSYS.Dim - Delivery.Delivery Creation Date",
      "localization" : {
        "localizationKey" : "Delivery Creation Date",
        "nameVariable" : "VALUEOF(NQ_SESSION.CN_SSYS_-_Sales_Orders_Delivery_Delivery_Creation_Date)",
        "descriptionVariable" : "VALUEOF(NQ_SESSION.CD_SSYS_-_Sales_Orders_Delivery_Delivery_Creation_Date)"
      }
    }, {
      "name" : "Delivery Last Update Date",
      "sourceLogicalColumn" : "logicalColumn:SSYS.Dim - Delivery.Delivery Last Update Date",
      "localization" : {
        "localizationKey" : "Delivery Last Update Date",
        "nameVariable" : "VALUEOF(NQ_SESSION.CN_SSYS_-_Sales_Orders_Delivery_Delivery_Last_Update_Date)",
        "descriptionVariable" : "VALUEOF(NQ_SESSION.CD_SSYS_-_Sales_Orders_Delivery_Delivery_Last_Update_Date)"
      }
    }, {
      "name" : "Delivery Status Code",
      "sourceLogicalColumn" : "logicalColumn:SSYS.Dim - Delivery.Delivery Status Code",
      "localization" : {
        "localizationKey" : "Delivery Status Code",
        "nameVariable" : "VALUEOF(NQ_SESSION.CN_SSYS_-_Sales_Orders_Delivery_Delivery_Status_Code)",
        "descriptionVariable" : "VALUEOF(NQ_SESSION.CD_SSYS_-_Sales_Orders_Delivery_Delivery_Status_Code)"
      }
    }, {
      "name" : "Delivery Type",
      "sourceLogicalColumn" : "logicalColumn:SSYS.Dim - Delivery.Delivery Type",
      "localization" : {
        "localizationKey" : "Delivery Type",
        "nameVariable" : "VALUEOF(NQ_SESSION.CN_SSYS_-_Sales_Orders_Delivery_Delivery_Type)",
        "descriptionVariable" : "VALUEOF(NQ_SESSION.CD_SSYS_-_Sales_Orders_Delivery_Delivery_Type)"
      }
    }, {
      "name" : "Description",
      "sourceLogicalColumn" : "logicalColumn:SSYS.Dim - Delivery.Description",
      "localization" : {
        "localizationKey" : "Description",
        "nameVariable" : "VALUEOF(NQ_SESSION.CN_SSYS_-_Sales_Orders_Delivery_Description)",
        "descriptionVariable" : "VALUEOF(NQ_SESSION.CD_SSYS_-_Sales_Orders_Delivery_Description)"
      }
    }, {
      "name" : "Mode Of Transport",
      "sourceLogicalColumn" : "logicalColumn:SSYS.Dim - Delivery.Mode Of Transport",
      "localization" : {
        "localizationKey" : "Mode Of Transport",
        "nameVariable" : "VALUEOF(NQ_SESSION.CN_SSYS_-_Sales_Orders_Delivery_Mode_Of_Transport)",
        "descriptionVariable" : "VALUEOF(NQ_SESSION.CD_SSYS_-_Sales_Orders_Delivery_Mode_Of_Transport)"
      }
    }, {
      "name" : "Number Of LPN",
      "sourceLogicalColumn" : "logicalColumn:SSYS.Dim - Delivery.Number Of LPN",
      "localization" : {
        "localizationKey" : "Number Of LPN",
        "nameVariable" : "VALUEOF(NQ_SESSION.CN_SSYS_-_Sales_Orders_Delivery_Number_Of_LPN)",
        "descriptionVariable" : "VALUEOF(NQ_SESSION.CD_SSYS_-_Sales_Orders_Delivery_Number_Of_LPN)"
      }
    }, {
      "name" : "Ship Method Code",
      "sourceLogicalColumn" : "logicalColumn:SSYS.Dim - Delivery.Ship Method Code",
      "localization" : {
        "localizationKey" : "Ship Method Code",
        "nameVariable" : "VALUEOF(NQ_SESSION.CN_SSYS_-_Sales_Orders_Delivery_Ship_Method_Code)",
        "descriptionVariable" : "VALUEOF(NQ_SESSION.CD_SSYS_-_Sales_Orders_Delivery_Ship_Method_Code)"
      }
    }, {
      "name" : "Ship Method Meaning",
      "sourceLogicalColumn" : "logicalColumn:SSYS.Dim - Delivery.Ship Method Meaning",
      "localization" : {
        "localizationKey" : "Ship Method Meaning",
        "nameVariable" : "VALUEOF(NQ_SESSION.CN_SSYS_-_Sales_Orders_Delivery_Ship_Method_Meaning)",
        "descriptionVariable" : "VALUEOF(NQ_SESSION.CD_SSYS_-_Sales_Orders_Delivery_Ship_Method_Meaning)"
      }
    }, {
      "name" : "Firm Status",
      "description" : "'Packed'/'Not Firm'/'Contents Firm'\r\n\r\nFormula:\r\n\r\nCASE \"SSYS\".\"Dim - Delivery\".\"Planned Flag\" \r\nWHEN 'N' THEN\r\nCASE  WHEN \"SSYS\".\"Dim - Delivery\".\"Attribute3\"='Y' THEN 'Packed'\r\nELSE 'Not Firm'\r\nEND\r\nWHEN 'Y' THEN 'Contents Firm'\r\nEND",
      "sourceLogicalColumn" : "logicalColumn:SSYS.Dim - Delivery.Firm Status",
      "alternateNames" : [ "firm_status" ],
      "localization" : {
        "localizationKey" : "Firm Status",
        "nameVariable" : "VALUEOF(NQ_SESSION.CN_SSYS_-_Sales_Orders_Delivery_Firm_Status)",
        "descriptionVariable" : "VALUEOF(NQ_SESSION.CD_SSYS_-_Sales_Orders_Delivery_Firm_Status)"
      }
    }, {
      "name" : "Initial Pickup Date",
      "sourceLogicalColumn" : "logicalColumn:SSYS.Dim - Delivery.Initial Pickup Date",
      "localization" : {
        "localizationKey" : "Initial Pickup Date",
        "nameVariable" : "VALUEOF(NQ_SESSION.CN_SSYS_-_Sales_Orders_Delivery_Initial_Pickup_Date)",
        "descriptionVariable" : "VALUEOF(NQ_SESSION.CD_SSYS_-_Sales_Orders_Delivery_Initial_Pickup_Date)"
      }
    }, {
      "name" : "Ultimate Dropoff Date",
      "sourceLogicalColumn" : "logicalColumn:SSYS.Dim - Delivery.Ultimate Dropoff Date",
      "localization" : {
        "localizationKey" : "Ultimate Dropoff Date",
        "nameVariable" : "VALUEOF(NQ_SESSION.CN_SSYS_-_Sales_Orders_Delivery_Ultimate_Dropoff_Date)",
        "descriptionVariable" : "VALUEOF(NQ_SESSION.CD_SSYS_-_Sales_Orders_Delivery_Ultimate_Dropoff_Date)"
      }
    }, {
      "name" : "Waybill",
      "sourceLogicalColumn" : "logicalColumn:SSYS.Dim - Delivery.Waybill",
      "localization" : {
        "localizationKey" : "Waybill",
        "nameVariable" : "VALUEOF(NQ_SESSION.CN_SSYS_-_Sales_Orders_Delivery_Waybill)",
        "descriptionVariable" : "VALUEOF(NQ_SESSION.CD_SSYS_-_Sales_Orders_Delivery_Waybill)"
      }
    }, {
      "name" : "Attribute1",
      "sourceLogicalColumn" : "logicalColumn:SSYS.Dim - Delivery.Attribute1",
      "localization" : {
        "localizationKey" : "Attribute1",
        "nameVariable" : "VALUEOF(NQ_SESSION.CN_SSYS_-_Sales_Orders_Delivery_Attribute1)",
        "descriptionVariable" : "VALUEOF(NQ_SESSION.CD_SSYS_-_Sales_Orders_Delivery_Attribute1)"
      }
    }, {
      "name" : "Attribute2",
      "sourceLogicalColumn" : "logicalColumn:SSYS.Dim - Delivery.Attribute2",
      "localization" : {
        "localizationKey" : "Attribute2",
        "nameVariable" : "VALUEOF(NQ_SESSION.CN_SSYS_-_Sales_Orders_Delivery_Attribute2)",
        "descriptionVariable" : "VALUEOF(NQ_SESSION.CD_SSYS_-_Sales_Orders_Delivery_Attribute2)"
      }
    }, {
      "name" : "Attribute3",
      "sourceLogicalColumn" : "logicalColumn:SSYS.Dim - Delivery.Attribute3",
      "localization" : {
        "localizationKey" : "Attribute3",
        "nameVariable" : "VALUEOF(NQ_SESSION.CN_SSYS_-_Sales_Orders_Delivery_Attribute3)",
        "descriptionVariable" : "VALUEOF(NQ_SESSION.CD_SSYS_-_Sales_Orders_Delivery_Attribute3)"
      }
    }, {
      "name" : "Attribute4",
      "sourceLogicalColumn" : "logicalColumn:SSYS.Dim - Delivery.Attribute4",
      "localization" : {
        "localizationKey" : "Attribute4",
        "nameVariable" : "VALUEOF(NQ_SESSION.CN_SSYS_-_Sales_Orders_Delivery_Attribute4)",
        "descriptionVariable" : "VALUEOF(NQ_SESSION.CD_SSYS_-_Sales_Orders_Delivery_Attribute4)"
      }
    }, {
      "name" : "Attribute5",
      "sourceLogicalColumn" : "logicalColumn:SSYS.Dim - Delivery.Attribute5",
      "localization" : {
        "localizationKey" : "Attribute5",
        "nameVariable" : "VALUEOF(NQ_SESSION.CN_SSYS_-_Sales_Orders_Delivery_Attribute5)",
        "descriptionVariable" : "VALUEOF(NQ_SESSION.CD_SSYS_-_Sales_Orders_Delivery_Attribute5)"
      }
    }, {
      "name" : "Attribute6",
      "sourceLogicalColumn" : "logicalColumn:SSYS.Dim - Delivery.Attribute6",
      "localization" : {
        "localizationKey" : "Attribute6",
        "nameVariable" : "VALUEOF(NQ_SESSION.CN_SSYS_-_Sales_Orders_Delivery_Attribute6)",
        "descriptionVariable" : "VALUEOF(NQ_SESSION.CD_SSYS_-_Sales_Orders_Delivery_Attribute6)"
      }
    }, {
      "name" : "Attribute7",
      "sourceLogicalColumn" : "logicalColumn:SSYS.Dim - Delivery.Attribute7",
      "localization" : {
        "localizationKey" : "Attribute7",
        "nameVariable" : "VALUEOF(NQ_SESSION.CN_SSYS_-_Sales_Orders_Delivery_Attribute7)",
        "descriptionVariable" : "VALUEOF(NQ_SESSION.CD_SSYS_-_Sales_Orders_Delivery_Attribute7)"
      }
    }, {
      "name" : "Attribute8",
      "sourceLogicalColumn" : "logicalColumn:SSYS.Dim - Delivery.Attribute8",
      "localization" : {
        "localizationKey" : "Attribute8",
        "nameVariable" : "VALUEOF(NQ_SESSION.CN_SSYS_-_Sales_Orders_Delivery_Attribute8)",
        "descriptionVariable" : "VALUEOF(NQ_SESSION.CD_SSYS_-_Sales_Orders_Delivery_Attribute8)"
      }
    }, {
      "name" : "Attribute9",
      "sourceLogicalColumn" : "logicalColumn:SSYS.Dim - Delivery.Attribute9",
      "localization" : {
        "localizationKey" : "Attribute9",
        "nameVariable" : "VALUEOF(NQ_SESSION.CN_SSYS_-_Sales_Orders_Delivery_Attribute9)",
        "descriptionVariable" : "VALUEOF(NQ_SESSION.CD_SSYS_-_Sales_Orders_Delivery_Attribute9)"
      }
    }, {
      "name" : "Estimated Time To Customer",
      "sourceLogicalColumn" : "logicalColumn:SSYS.Dim - Delivery.Estimated Time To Customer",
      "localization" : {
        "localizationKey" : "Estimated Time To Customer",
        "nameVariable" : "VALUEOF(NQ_SESSION.CN_SSYS_-_Sales_Orders_Delivery_Estimated_Time_To_Customer)",
        "descriptionVariable" : "VALUEOF(NQ_SESSION.CD_SSYS_-_Sales_Orders_Delivery_Estimated_Time_To_Customer)"
      }
    }, {
      "name" : "Pod Signed Date",
      "sourceLogicalColumn" : "logicalColumn:SSYS.Dim - Delivery.Pod Signed Date",
      "localization" : {
        "localizationKey" : "Pod Signed Date",
        "nameVariable" : "VALUEOF(NQ_SESSION.CN_SSYS_-_Sales_Orders_Delivery_Pod_Signed_Date)",
        "descriptionVariable" : "VALUEOF(NQ_SESSION.CD_SSYS_-_Sales_Orders_Delivery_Pod_Signed_Date)"
      }
    }, {
      "name" : "Estimated Freight Cost",
      "sourceLogicalColumn" : "logicalColumn:SSYS.Dim - Delivery.Estimated Freight Cost",
      "localization" : {
        "localizationKey" : "Estimated Freight Cost",
        "nameVariable" : "VALUEOF(NQ_SESSION.CN_SSYS_-_Sales_Orders_Delivery_Estimated_Freight_Cost)",
        "descriptionVariable" : "VALUEOF(NQ_SESSION.CD_SSYS_-_Sales_Orders_Delivery_Estimated_Freight_Cost)"
      }
    }, {
      "name" : "Export Entry",
      "sourceLogicalColumn" : "logicalColumn:SSYS.Dim - Delivery.Export Entry",
      "localization" : {
        "localizationKey" : "Export Entry",
        "nameVariable" : "VALUEOF(NQ_SESSION.CN_SSYS_-_Sales_Orders_Delivery_Export_Entry)",
        "descriptionVariable" : "VALUEOF(NQ_SESSION.CD_SSYS_-_Sales_Orders_Delivery_Export_Entry)"
      }
    }, {
      "name" : "Volume",
      "sourceLogicalColumn" : "logicalColumn:SSYS.Dim - Delivery.Volume",
      "localization" : {
        "localizationKey" : "Volume",
        "nameVariable" : "VALUEOF(NQ_SESSION.CN_SSYS_-_Sales_Orders_Delivery_Volume)",
        "descriptionVariable" : "VALUEOF(NQ_SESSION.CD_SSYS_-_Sales_Orders_Delivery_Volume)"
      }
    }, {
      "name" : "Volume Uom Code",
      "sourceLogicalColumn" : "logicalColumn:SSYS.Dim - Delivery.Volume Uom Code",
      "localization" : {
        "localizationKey" : "Volume Uom Code",
        "nameVariable" : "VALUEOF(NQ_SESSION.CN_SSYS_-_Sales_Orders_Delivery_Volume_Uom_Code)",
        "descriptionVariable" : "VALUEOF(NQ_SESSION.CD_SSYS_-_Sales_Orders_Delivery_Volume_Uom_Code)"
      }
    }, {
      "name" : "Weight Uom Code",
      "sourceLogicalColumn" : "logicalColumn:SSYS.Dim - Delivery.Weight Uom Code",
      "localization" : {
        "localizationKey" : "Weight Uom Code",
        "nameVariable" : "VALUEOF(NQ_SESSION.CN_SSYS_-_Sales_Orders_Delivery_Weight_Uom_Code)",
        "descriptionVariable" : "VALUEOF(NQ_SESSION.CD_SSYS_-_Sales_Orders_Delivery_Weight_Uom_Code)"
      }
    }, {
      "name" : "Gross Weight",
      "sourceLogicalColumn" : "logicalColumn:SSYS.Dim - Delivery.Gross Weight",
      "localization" : {
        "localizationKey" : "Gross Weight",
        "nameVariable" : "VALUEOF(NQ_SESSION.CN_SSYS_-_Sales_Orders_Delivery_Gross_Weight)",
        "descriptionVariable" : "VALUEOF(NQ_SESSION.CD_SSYS_-_Sales_Orders_Delivery_Gross_Weight)"
      }
    } ],
    "localization" : {
      "localizationKey" : "Delivery",
      "nameVariable" : "VALUEOF(NQ_SESSION.CN_SSYS_-_Sales_Orders_Delivery)",
      "descriptionVariable" : "VALUEOF(NQ_SESSION.CD_SSYS_-_Sales_Orders_Delivery)"
    }
  }
}