{
  "physicalTable" : {
    "name" : "XXOM_K2_ORDERPICK_STATUS_V",
    "sourceType" : "TABLE",
    "physicalColumns" : [ {
      "name" : "ATTRIBUTE1",
      "dataType" : "VARCHAR",
      "length" : 100,
      "nullable" : true
    }, {
      "name" : "ATTRIBUTE2",
      "dataType" : "VARCHAR",
      "length" : 100,
      "nullable" : true
    }, {
      "name" : "ATTRIBUTE3",
      "dataType" : "VARCHAR",
      "length" : 100,
      "nullable" : true
    }, {
      "name" : "ATTRIBUTE4",
      "dataType" : "VARCHAR",
      "length" : 100,
      "nullable" : true
    }, {
      "name" : "ATTRIBUTE5",
      "dataType" : "VARCHAR",
      "length" : 100,
      "nullable" : true
    }, {
      "name" : "ATTRIBUTE6",
      "dataType" : "VARCHAR",
      "length" : 100,
      "nullable" : true
    }, {
      "name" : "ATTRIBUTE7",
      "dataType" : "VARCHAR",
      "length" : 100,
      "nullable" : true
    }, {
      "name" : "ATTRIBUTE8",
      "dataType" : "VARCHAR",
      "length" : 100,
      "nullable" : true
    }, {
      "name" : "BILL_TO_CUST_SITE_USE_ID",
      "dataType" : "INT",
      "length" : 0,
      "nullable" : true
    }, {
      "name" : "CONFIRMATION_DATE",
      "dataType" : "DATE",
      "length" : 0,
      "nullable" : true
    }, {
      "name" : "CREATED_BY",
      "dataType" : "INT",
      "length" : 0,
      "nullable" : true
    }, {
      "name" : "CREATION_DATE",
      "dataType" : "DATETIME",
      "length" : 0,
      "nullable" : true
    }, {
      "name" : "DATE_REC_PROCESSED",
      "dataType" : "DATETIME",
      "length" : 0,
      "nullable" : true
    }, {
      "name" : "DELIVERY_DETAIL_ID",
      "dataType" : "INT",
      "length" : 0,
      "nullable" : true
    }, {
      "name" : "DELIVERY_ID",
      "dataType" : "INT",
      "length" : 0,
      "nullable" : true
    }, {
      "name" : "ERROR_MESSAGE",
      "dataType" : "VARCHAR",
      "length" : 2000,
      "nullable" : true
    }, {
      "name" : "FILE_NAME",
      "dataType" : "VARCHAR",
      "length" : 1000,
      "nullable" : true
    }, {
      "name" : "FREIGHT_CARRIER_CODE",
      "dataType" : "VARCHAR",
      "length" : 50,
      "nullable" : true
    }, {
      "name" : "FROM_SUBINV",
      "dataType" : "VARCHAR",
      "length" : 100,
      "nullable" : true
    }, {
      "name" : "INVENTORY_ITEM_ID",
      "dataType" : "INT",
      "length" : 0,
      "nullable" : true
    }, {
      "name" : "LAST_UPDATED_BY",
      "dataType" : "INT",
      "length" : 0,
      "nullable" : true
    }, {
      "name" : "LAST_UPDATE_DATE",
      "dataType" : "DATETIME",
      "length" : 0,
      "nullable" : true
    }, {
      "name" : "MO_LINE_NUMBER",
      "dataType" : "INT",
      "length" : 0,
      "nullable" : true
    }, {
      "name" : "ORGANIZATION_ID",
      "dataType" : "INT",
      "length" : 0,
      "nullable" : true
    }, {
      "name" : "ORG_ID",
      "dataType" : "INT",
      "length" : 0,
      "nullable" : true
    }, {
      "name" : "PICK_RELEASED_DATE",
      "dataType" : "DATETIME",
      "length" : 0,
      "nullable" : true
    }, {
      "name" : "PICK_SLIP_NUMBER",
      "dataType" : "DOUBLE",
      "length" : 0,
      "nullable" : true
    }, {
      "name" : "QTY",
      "dataType" : "DOUBLE",
      "length" : 0,
      "nullable" : true
    }, {
      "name" : "REC_PROCESSED_FLAG",
      "dataType" : "VARCHAR",
      "length" : 100,
      "nullable" : true
    }, {
      "name" : "SCHEDULE_SHIP_DATE",
      "dataType" : "VARCHAR",
      "length" : 50,
      "nullable" : true
    }, {
      "name" : "SEQUENCE_NUMBER",
      "dataType" : "DOUBLE",
      "length" : 0,
      "nullable" : true
    }, {
      "name" : "SHIP_METHOD",
      "dataType" : "VARCHAR",
      "length" : 150,
      "nullable" : true
    }, {
      "name" : "SHIP_TO_CUST_SITE_USE_ID",
      "dataType" : "INT",
      "length" : 0,
      "nullable" : true
    }, {
      "name" : "SOURCE",
      "dataType" : "VARCHAR",
      "length" : 100,
      "nullable" : true
    }, {
      "name" : "SOURCE_HEADER_ID",
      "dataType" : "INT",
      "length" : 0,
      "nullable" : true
    }, {
      "name" : "SOURCE_LINE_ID",
      "dataType" : "INT",
      "length" : 0,
      "nullable" : true
    }, {
      "name" : "UOM",
      "dataType" : "VARCHAR",
      "length" : 10,
      "nullable" : true
    }, {
      "name" : "DATE_REC_PROCESSED_TRUNC",
      "dataType" : "DATE",
      "length" : 0,
      "nullable" : true
    }, {
      "name" : "DATE_REC_PROCESSED_CHAR",
      "dataType" : "VARCHAR",
      "length" : 100,
      "nullable" : true
    }, {
      "name" : "PICK_RELEASED_DATE_TRUNC",
      "dataType" : "DATE",
      "length" : 0,
      "nullable" : true
    }, {
      "name" : "K2_ORDER_STATUS",
      "dataType" : "VARCHAR",
      "length" : 150,
      "nullable" : true
    }, {
      "name" : "TRACKING_NUMBERS",
      "dataType" : "VARCHAR",
      "length" : 1000,
      "nullable" : true
    }, {
      "name" : "K2_FILE_RECEIVE_DATE_TRUNC",
      "dataType" : "DATE",
      "length" : 0,
      "nullable" : true
    }, {
      "name" : "K2_ORDER_STATUS_DATE_TRUNC",
      "dataType" : "DATE",
      "length" : 0,
      "nullable" : true
    }, {
      "name" : "K2_FILE_RECEIVE_DATE",
      "dataType" : "DATETIME",
      "length" : 0,
      "nullable" : true
    }, {
      "name" : "K2_ORDER_STATUS_DATE",
      "dataType" : "DATETIME",
      "length" : 0,
      "nullable" : true
    } ]
  }
}