{
  "physicalTable" : {
    "name" : "XXPO_REQUISITIONS_V",
    "sourceType" : "TABLE",
    "physicalColumns" : [ {
      "name" : "PR_HEADER_ID",
      "dataType" : "DOUBLE",
      "length" : 38,
      "nullable" : true
    }, {
      "name" : "PR_NUMBER",
      "dataType" : "VARCHAR",
      "length" : 20,
      "nullable" : true
    }, {
      "name" : "PR_CLOSED_CODE",
      "dataType" : "VARCHAR",
      "length" : 25,
      "nullable" : true
    }, {
      "name" : "PR_AUTHORIZATION_STATUS",
      "dataType" : "VARCHAR",
      "length" : 25,
      "nullable" : true
    }, {
      "name" : "PR_LAST_UPDATE_DATE",
      "dataType" : "DATE",
      "length" : 0,
      "nullable" : true
    }, {
      "name" : "PR_CREATION_DATE",
      "dataType" : "DATE",
      "length" : 0,
      "nullable" : true
    }, {
      "name" : "PR_HEADER_DESCRIPTION",
      "dataType" : "VARCHAR",
      "length" : 240,
      "nullable" : true
    }, {
      "name" : "PR_NOTE_TO_AUTHORIZER",
      "dataType" : "VARCHAR",
      "length" : 4000,
      "nullable" : true
    }, {
      "name" : "PR_TYPE",
      "dataType" : "VARCHAR",
      "length" : 25,
      "nullable" : true
    }, {
      "name" : "PR_HEADER_CANCEL_FLAG",
      "dataType" : "VARCHAR",
      "length" : 1,
      "nullable" : true
    }, {
      "name" : "PR_HEADER_ATTRIBUTE1",
      "dataType" : "VARCHAR",
      "length" : 150,
      "nullable" : true
    }, {
      "name" : "PR_HEADER_ATTRIBUTE2",
      "dataType" : "VARCHAR",
      "length" : 150,
      "nullable" : true
    }, {
      "name" : "PR_HEADER_ATTRIBUTE3",
      "dataType" : "VARCHAR",
      "length" : 150,
      "nullable" : true
    }, {
      "name" : "PR_HEADER_ATTRIBUTE4",
      "dataType" : "VARCHAR",
      "length" : 150,
      "nullable" : true
    }, {
      "name" : "PR_HEADER_ATTRIBUTE5",
      "dataType" : "VARCHAR",
      "length" : 150,
      "nullable" : true
    }, {
      "name" : "PR_HEADER_ATTRIBUTE6",
      "dataType" : "VARCHAR",
      "length" : 150,
      "nullable" : true
    }, {
      "name" : "PR_HEADER_ATTRIBUTE7",
      "dataType" : "VARCHAR",
      "length" : 150,
      "nullable" : true
    }, {
      "name" : "PR_HEADER_ATTRIBUTE8",
      "dataType" : "VARCHAR",
      "length" : 150,
      "nullable" : true
    }, {
      "name" : "PR_HEADER_ATTRIBUTE9",
      "dataType" : "VARCHAR",
      "length" : 150,
      "nullable" : true
    }, {
      "name" : "PR_HEADER_ATTRIBUTE10",
      "dataType" : "VARCHAR",
      "length" : 150,
      "nullable" : true
    }, {
      "name" : "ORG_ID",
      "dataType" : "DOUBLE",
      "length" : 38,
      "nullable" : true
    }, {
      "name" : "PR_HEADER_APPROVED_DATE",
      "dataType" : "DATE",
      "length" : 0,
      "nullable" : true
    }, {
      "name" : "REQUISITION_LINE_ID",
      "dataType" : "DOUBLE",
      "length" : 38,
      "nullable" : true
    }, {
      "name" : "PR_LINE_NUMBER",
      "dataType" : "DOUBLE",
      "length" : 38,
      "nullable" : true
    }, {
      "name" : "CATEGORY_ID",
      "dataType" : "DOUBLE",
      "length" : 38,
      "nullable" : true
    }, {
      "name" : "ITEM_ID",
      "dataType" : "DOUBLE",
      "length" : 38,
      "nullable" : true
    }, {
      "name" : "ITEM_DESCRIPTION",
      "dataType" : "VARCHAR",
      "length" : 240,
      "nullable" : true
    }, {
      "name" : "UNIT_MEAS_LOOKUP_CODE",
      "dataType" : "VARCHAR",
      "length" : 25,
      "nullable" : true
    }, {
      "name" : "UNIT_PRICE",
      "dataType" : "DOUBLE",
      "length" : 38,
      "nullable" : true
    }, {
      "name" : "QUANTITY",
      "dataType" : "DOUBLE",
      "length" : 38,
      "nullable" : true
    }, {
      "name" : "QUANTITY_DELIVERED",
      "dataType" : "DOUBLE",
      "length" : 38,
      "nullable" : true
    }, {
      "name" : "QUANTITY_CANCELLED",
      "dataType" : "DOUBLE",
      "length" : 38,
      "nullable" : true
    }, {
      "name" : "ENCUMBERED_FLAG",
      "dataType" : "VARCHAR",
      "length" : 1,
      "nullable" : true
    }, {
      "name" : "LINE_NEED_BY_DATE",
      "dataType" : "DATE",
      "length" : 0,
      "nullable" : true
    }, {
      "name" : "LINE_CREATION_DATE",
      "dataType" : "DATE",
      "length" : 0,
      "nullable" : true
    }, {
      "name" : "LINE_LAST_UPDATE_DATE",
      "dataType" : "DATE",
      "length" : 0,
      "nullable" : true
    }, {
      "name" : "LINE_SOURCE_TYPE",
      "dataType" : "VARCHAR",
      "length" : 25,
      "nullable" : true
    }, {
      "name" : "LINE_CANCEL_FLAG",
      "dataType" : "VARCHAR",
      "length" : 1,
      "nullable" : true
    }, {
      "name" : "LINE_CANCEL_DATE",
      "dataType" : "DATE",
      "length" : 0,
      "nullable" : true
    }, {
      "name" : "LINE_JUSTIFICATION",
      "dataType" : "VARCHAR",
      "length" : 480,
      "nullable" : true
    }, {
      "name" : "LINE_NOTE_TO_AGENT",
      "dataType" : "VARCHAR",
      "length" : 480,
      "nullable" : true
    }, {
      "name" : "VENDOR_ID",
      "dataType" : "DOUBLE",
      "length" : 38,
      "nullable" : true
    }, {
      "name" : "VENDOR_SITE_ID",
      "dataType" : "DOUBLE",
      "length" : 38,
      "nullable" : true
    }, {
      "name" : "PR_LINE_ATTRIBUTE1",
      "dataType" : "VARCHAR",
      "length" : 150,
      "nullable" : true
    }, {
      "name" : "PR_LINE_ATTRIBUTE2",
      "dataType" : "VARCHAR",
      "length" : 150,
      "nullable" : true
    }, {
      "name" : "PR_LINE_ATTRIBUTE3",
      "dataType" : "VARCHAR",
      "length" : 150,
      "nullable" : true
    }, {
      "name" : "PR_LINE_ATTRIBUTE4",
      "dataType" : "VARCHAR",
      "length" : 150,
      "nullable" : true
    }, {
      "name" : "PR_LINE_ATTRIBUTE5",
      "dataType" : "VARCHAR",
      "length" : 150,
      "nullable" : true
    }, {
      "name" : "PR_LINE_ATTRIBUTE6",
      "dataType" : "VARCHAR",
      "length" : 150,
      "nullable" : true
    }, {
      "name" : "PR_LINE_ATTRIBUTE7",
      "dataType" : "VARCHAR",
      "length" : 150,
      "nullable" : true
    }, {
      "name" : "PR_LINE_ATTRIBUTE8",
      "dataType" : "VARCHAR",
      "length" : 150,
      "nullable" : true
    }, {
      "name" : "PR_LINE_ATTRIBUTE9",
      "dataType" : "VARCHAR",
      "length" : 150,
      "nullable" : true
    }, {
      "name" : "PR_LINE_ATTRIBUTE10",
      "dataType" : "VARCHAR",
      "length" : 150,
      "nullable" : true
    }, {
      "name" : "PR_DISTRIBUTION_ID",
      "dataType" : "DOUBLE",
      "length" : 38,
      "nullable" : true
    }, {
      "name" : "DISTRIBUTION_NUM",
      "dataType" : "DOUBLE",
      "length" : 38,
      "nullable" : true
    }, {
      "name" : "PR_DIST_CREATION_DATE",
      "dataType" : "DATE",
      "length" : 0,
      "nullable" : true
    }, {
      "name" : "PR_DIST_LAST_UPDATE_DATE",
      "dataType" : "DATE",
      "length" : 0,
      "nullable" : true
    }, {
      "name" : "SET_OF_BOOKS_ID",
      "dataType" : "DOUBLE",
      "length" : 38,
      "nullable" : true
    }, {
      "name" : "CODE_COMBINATION_ID",
      "dataType" : "DOUBLE",
      "length" : 38,
      "nullable" : true
    }, {
      "name" : "REQ_LINE_QUANTITY",
      "dataType" : "DOUBLE",
      "length" : 38,
      "nullable" : true
    }, {
      "name" : "FAILED_FUNDS_LOOKUP_CODE",
      "dataType" : "VARCHAR",
      "length" : 25,
      "nullable" : true
    }, {
      "name" : "PR_DIST_ENCUMBERED_AMOUNT",
      "dataType" : "DOUBLE",
      "length" : 38,
      "nullable" : true
    }, {
      "name" : "ACCRUAL_ACCOUNT_ID",
      "dataType" : "DOUBLE",
      "length" : 38,
      "nullable" : true
    }, {
      "name" : "BUDGET_ACCOUNT_ID",
      "dataType" : "DOUBLE",
      "length" : 38,
      "nullable" : true
    }, {
      "name" : "PR_DIST_ATTRIBUTE1",
      "dataType" : "VARCHAR",
      "length" : 150,
      "nullable" : true
    }, {
      "name" : "PR_DIST_ATTRIBUTE2",
      "dataType" : "VARCHAR",
      "length" : 150,
      "nullable" : true
    }, {
      "name" : "PR_DIST_ATTRIBUTE3",
      "dataType" : "VARCHAR",
      "length" : 150,
      "nullable" : true
    }, {
      "name" : "PR_DIST_ATTRIBUTE4",
      "dataType" : "VARCHAR",
      "length" : 150,
      "nullable" : true
    }, {
      "name" : "PR_DIST_ATTRIBUTE5",
      "dataType" : "VARCHAR",
      "length" : 150,
      "nullable" : true
    }, {
      "name" : "PR_DIST_ATTRIBUTE6",
      "dataType" : "VARCHAR",
      "length" : 150,
      "nullable" : true
    }, {
      "name" : "PR_DIST_ATTRIBUTE7",
      "dataType" : "VARCHAR",
      "length" : 150,
      "nullable" : true
    }, {
      "name" : "PR_DIST_ATTRIBUTE8",
      "dataType" : "VARCHAR",
      "length" : 150,
      "nullable" : true
    }, {
      "name" : "PR_DIST_ATTRIBUTE9",
      "dataType" : "VARCHAR",
      "length" : 150,
      "nullable" : true
    }, {
      "name" : "PR_DIST_ATTRIBUTE10",
      "dataType" : "VARCHAR",
      "length" : 150,
      "nullable" : true
    }, {
      "name" : "PR_GL_ENCUMBERED_DATE",
      "dataType" : "DATE",
      "length" : 0,
      "nullable" : true
    }, {
      "name" : "PR_EXPENDITURE_ITEM_DATE",
      "dataType" : "DATE",
      "length" : 0,
      "nullable" : true
    }, {
      "name" : "PR_ENBUMBERED_PERIOD_NAME",
      "dataType" : "VARCHAR",
      "length" : 15,
      "nullable" : true
    }, {
      "name" : "PREVENT_ENCUMBRANCE_FLAG",
      "dataType" : "VARCHAR",
      "length" : 1,
      "nullable" : true
    }, {
      "name" : "PROJECT_ID",
      "dataType" : "DOUBLE",
      "length" : 38,
      "nullable" : true
    }, {
      "name" : "TASK_ID",
      "dataType" : "DOUBLE",
      "length" : 38,
      "nullable" : true
    }, {
      "name" : "EXPENDITURE_TYPE",
      "dataType" : "VARCHAR",
      "length" : 30,
      "nullable" : true
    }, {
      "name" : "EXPENDITURE_ORGANIZATION_ID",
      "dataType" : "DOUBLE",
      "length" : 38,
      "nullable" : true
    }, {
      "name" : "AWARD_ID",
      "dataType" : "DOUBLE",
      "length" : 38,
      "nullable" : true
    }, {
      "name" : "REQUESTOR_ID",
      "dataType" : "DOUBLE",
      "length" : 0,
      "nullable" : false
    }, {
      "name" : "PREPARER_ID",
      "dataType" : "DOUBLE",
      "length" : 0,
      "nullable" : false
    }, {
      "name" : "PL_LINE_LOCATION_ID",
      "dataType" : "DOUBLE",
      "length" : 0,
      "nullable" : true
    }, {
      "name" : "BUYER_ID",
      "dataType" : "DOUBLE",
      "length" : 0,
      "nullable" : true
    }, {
      "name" : "AUTO_CREATED_FLAG",
      "dataType" : "VARCHAR",
      "length" : 10,
      "nullable" : true
    } ]
  }
}