{
  "presentationTable" : {
    "name" : "ETL Data Quality Results",
    "presentationColumns" : [ {
      "name" : "Dq Module Name",
      "sourceLogicalColumn" : "logicalColumn:XXControl.ETL Data Quality Results.Dq Module Name",
      "localization" : {
        "localizationKey" : "Dq Module Name",
        "nameVariable" : "VALUEOF(NQ_SESSION.CN_XXControl_ETL_Data_Quality_Results_Dq_Module_Name)",
        "descriptionVariable" : "VALUEOF(NQ_SESSION.CD_XXControl_ETL_Data_Quality_Results_Dq_Module_Name)"
      }
    }, {
      "name" : "Dq Group Name",
      "sourceLogicalColumn" : "logicalColumn:XXControl.ETL Data Quality Results.Dq Group Name",
      "localization" : {
        "localizationKey" : "Dq Group Name",
        "nameVariable" : "VALUEOF(NQ_SESSION.CN_XXControl_ETL_Data_Quality_Results_Dq_Group_Name)",
        "descriptionVariable" : "VALUEOF(NQ_SESSION.CD_XXControl_ETL_Data_Quality_Results_Dq_Group_Name)"
      }
    }, {
      "name" : "Dq Status Flag",
      "sourceLogicalColumn" : "logicalColumn:XXControl.ETL Data Quality Results.Dq Status Flag",
      "localization" : {
        "localizationKey" : "Dq Status Flag",
        "nameVariable" : "VALUEOF(NQ_SESSION.CN_XXControl_ETL_Data_Quality_Results_Dq_Status_Flag)",
        "descriptionVariable" : "VALUEOF(NQ_SESSION.CD_XXControl_ETL_Data_Quality_Results_Dq_Status_Flag)"
      }
    }, {
      "name" : "Target Column Name",
      "sourceLogicalColumn" : "logicalColumn:XXControl.ETL Data Quality Results.Target Column Name",
      "localization" : {
        "localizationKey" : "Target Column Name",
        "nameVariable" : "VALUEOF(NQ_SESSION.CN_XXControl_ETL_Data_Quality_Results_Target_Column_Name)",
        "descriptionVariable" : "VALUEOF(NQ_SESSION.CD_XXControl_ETL_Data_Quality_Results_Target_Column_Name)"
      }
    }, {
      "name" : "Target Schema Name",
      "sourceLogicalColumn" : "logicalColumn:XXControl.ETL Data Quality Results.Target Schema Name",
      "localization" : {
        "localizationKey" : "Target Schema Name",
        "nameVariable" : "VALUEOF(NQ_SESSION.CN_XXControl_ETL_Data_Quality_Results_Target_Schema_Name)",
        "descriptionVariable" : "VALUEOF(NQ_SESSION.CD_XXControl_ETL_Data_Quality_Results_Target_Schema_Name)"
      }
    }, {
      "name" : "Target Table Name",
      "sourceLogicalColumn" : "logicalColumn:XXControl.ETL Data Quality Results.Target Table Name",
      "localization" : {
        "localizationKey" : "Target Table Name",
        "nameVariable" : "VALUEOF(NQ_SESSION.CN_XXControl_ETL_Data_Quality_Results_Target_Table_Name)",
        "descriptionVariable" : "VALUEOF(NQ_SESSION.CD_XXControl_ETL_Data_Quality_Results_Target_Table_Name)"
      }
    }, {
      "name" : "Dq Check Date",
      "sourceLogicalColumn" : "logicalColumn:XXControl.ETL Data Quality Results.Dq Check Date",
      "localization" : {
        "localizationKey" : "Dq Check Date",
        "nameVariable" : "VALUEOF(NQ_SESSION.CN_XXControl_ETL_Data_Quality_Results_Dq_Check_Date)",
        "descriptionVariable" : "VALUEOF(NQ_SESSION.CD_XXControl_ETL_Data_Quality_Results_Dq_Check_Date)"
      }
    }, {
      "name" : "Dq Check Rule",
      "sourceLogicalColumn" : "logicalColumn:XXControl.ETL Data Quality Results.Dq Check Rule",
      "localization" : {
        "localizationKey" : "Dq Check Rule",
        "nameVariable" : "VALUEOF(NQ_SESSION.CN_XXControl_ETL_Data_Quality_Results_Dq_Check_Rule)",
        "descriptionVariable" : "VALUEOF(NQ_SESSION.CD_XXControl_ETL_Data_Quality_Results_Dq_Check_Rule)"
      }
    }, {
      "name" : "DQ Total Record Count",
      "sourceLogicalColumn" : "logicalColumn:XXControl.ETL Data Quality Results.DQ Total Record Count",
      "alternateNames" : [ "Dq Total Rec Cnt", "DQ Total Rec Count" ],
      "localization" : {
        "localizationKey" : "DQ Total Record Count",
        "nameVariable" : "VALUEOF(NQ_SESSION.CN_XXControl_ETL_Data_Quality_Results_DQ_Total_Record_Count)",
        "descriptionVariable" : "VALUEOF(NQ_SESSION.CD_XXControl_ETL_Data_Quality_Results_DQ_Total_Record_Count)"
      }
    }, {
      "name" : "DQ Pass Record Count",
      "sourceLogicalColumn" : "logicalColumn:XXControl.ETL Data Quality Results.DQ Pass Record Count",
      "alternateNames" : [ "Dq Pass Rec Cnt" ],
      "localization" : {
        "localizationKey" : "DQ Pass Record Count",
        "nameVariable" : "VALUEOF(NQ_SESSION.CN_XXControl_ETL_Data_Quality_Results_DQ_Pass_Record_Count)",
        "descriptionVariable" : "VALUEOF(NQ_SESSION.CD_XXControl_ETL_Data_Quality_Results_DQ_Pass_Record_Count)"
      }
    }, {
      "name" : "DQ Fail Record Count",
      "sourceLogicalColumn" : "logicalColumn:XXControl.ETL Data Quality Results.DQ Fail Record Count",
      "alternateNames" : [ "Dq Fail Rec Cnt" ],
      "localization" : {
        "localizationKey" : "DQ Fail Record Count",
        "nameVariable" : "VALUEOF(NQ_SESSION.CN_XXControl_ETL_Data_Quality_Results_DQ_Fail_Record_Count)",
        "descriptionVariable" : "VALUEOF(NQ_SESSION.CD_XXControl_ETL_Data_Quality_Results_DQ_Fail_Record_Count)"
      }
    }, {
      "name" : "DQ Default Record Count",
      "sourceLogicalColumn" : "logicalColumn:XXControl.ETL Data Quality Results.DQ Default Record Count",
      "alternateNames" : [ "Dq Default Rec Cnt" ],
      "localization" : {
        "localizationKey" : "DQ Default Record Count",
        "nameVariable" : "VALUEOF(NQ_SESSION.CN_XXControl_ETL_Data_Quality_Results_DQ_Default_Record_Count)",
        "descriptionVariable" : "VALUEOF(NQ_SESSION.CD_XXControl_ETL_Data_Quality_Results_DQ_Default_Record_Count)"
      }
    } ],
    "localization" : {
      "localizationKey" : "ETL Data Quality Results",
      "nameVariable" : "VALUEOF(NQ_SESSION.CN_XXControl_ETL_Data_Quality_Results)",
      "descriptionVariable" : "VALUEOF(NQ_SESSION.CD_XXControl_ETL_Data_Quality_Results)"
    }
  }
}