{
  "presentationTable" : {
    "name" : "Supply Pegging Measures",
    "presentationColumns" : [ {
      "name" : "Indication Text",
      "sourceLogicalColumn" : "logicalColumn:SSYS.Dim - Current-History Indication.Indication Text",
      "localization" : {
        "localizationKey" : "Indication Text",
        "nameVariable" : "VALUEOF(NQ_SESSION.CN_SSYS_-_Purchasing_Planning_Supply_Pegging_Measures_Indication_Text)",
        "descriptionVariable" : "VALUEOF(NQ_SESSION.CD_SSYS_-_Purchasing_Planning_Supply_Pegging_Measures_Indication_Text)"
      }
    }, {
      "name" : "Purch Item Allocated Qty",
      "sourceLogicalColumn" : "logicalColumn:SSYS.Fact - Purchasing Supply Pegging.Purch Item Allocated Qty",
      "alternateNames" : [ "PURCH_ITEM_ALLOCATED_QTY" ],
      "localization" : {
        "localizationKey" : "Purch Item Allocated Qty",
        "nameVariable" : "VALUEOF(NQ_SESSION.CN_SSYS_-_Purchasing_Planning_Supply_Pegging_Measures_Purch_Item_Allocated_Qty)",
        "descriptionVariable" : "VALUEOF(NQ_SESSION.CD_SSYS_-_Purchasing_Planning_Supply_Pegging_Measures_Purch_Item_Allocated_Qty)"
      }
    } ],
    "localization" : {
      "localizationKey" : "Supply Pegging Measures",
      "nameVariable" : "VALUEOF(NQ_SESSION.CN_SSYS_-_Purchasing_Planning_Supply_Pegging_Measures)",
      "descriptionVariable" : "VALUEOF(NQ_SESSION.CD_SSYS_-_Purchasing_Planning_Supply_Pegging_Measures)"
    }
  }
}